yapf/__init__.py
yapf/__main__.py
yapf/pyparser/__init__.py
yapf/pyparser/pyparser.py
yapf/pyparser/pyparser_utils.py
yapf/pyparser/split_penalty_visitor.py
yapf/pytree/__init__.py
yapf/pytree/blank_line_calculator.py
yapf/pytree/comment_splicer.py
yapf/pytree/continuation_splicer.py
yapf/pytree/pytree_unwrapper.py
yapf/pytree/pytree_utils.py
yapf/pytree/pytree_visitor.py
yapf/pytree/split_penalty.py
yapf/pytree/subtype_assigner.py
yapf/yapflib/__init__.py
yapf/yapflib/errors.py
yapf/yapflib/file_resources.py
yapf/yapflib/format_decision_state.py
yapf/yapflib/format_token.py
yapf/yapflib/identify_container.py
yapf/yapflib/line_joiner.py
yapf/yapflib/logical_line.py
yapf/yapflib/object_state.py
yapf/yapflib/reformatter.py
yapf/yapflib/split_penalty.py
yapf/yapflib/style.py
yapf/yapflib/subtypes.py
yapf/yapflib/verifier.py
yapf/yapflib/yapf_api.py
yapf_third_party/__init__.py
yapf_third_party/_ylib2to3/Grammar.txt
yapf_third_party/_ylib2to3/LICENSE
yapf_third_party/_ylib2to3/PatternGrammar.txt
yapf_third_party/_ylib2to3/__init__.py
yapf_third_party/_ylib2to3/fixer_util.py
yapf_third_party/_ylib2to3/patcomp.py
yapf_third_party/_ylib2to3/pygram.py
yapf_third_party/_ylib2to3/pytree.py
yapf_third_party/_ylib2to3/pgen2/__init__.py
yapf_third_party/_ylib2to3/pgen2/conv.py
yapf_third_party/_ylib2to3/pgen2/driver.py
yapf_third_party/_ylib2to3/pgen2/grammar.py
yapf_third_party/_ylib2to3/pgen2/literals.py
yapf_third_party/_ylib2to3/pgen2/parse.py
yapf_third_party/_ylib2to3/pgen2/pgen.py
yapf_third_party/_ylib2to3/pgen2/token.py
yapf_third_party/_ylib2to3/pgen2/tokenize.py
yapf_third_party/yapf_diff/LICENSE
yapf_third_party/yapf_diff/__init__.py
yapf_third_party/yapf_diff/yapf_diff.py
yapftests/__init__.py
yapftests/blank_line_calculator_test.py
yapftests/comment_splicer_test.py
yapftests/file_resources_test.py
yapftests/format_decision_state_test.py
yapftests/format_token_test.py
yapftests/line_joiner_test.py
yapftests/logical_line_test.py
yapftests/main_test.py
yapf-0.40.1.dist-info/AUTHORS
yapf-0.40.1.dist-info/LICENSE
yapf-0.40.1.dist-info/METADATA
yapf-0.40.1.dist-info/WHEEL
yapf-0.40.1.dist-info/entry_points.txt
yapf-0.40.1.dist-info/top_level.txt
yapf-0.40.1.dist-info/RECORD
