Metadata-Version: 2.1
Name: yapf
Version: 0.40.1
Summary: A formatter for Python code.
Home-page: https://github.com/google/yapf
Author: Google Inc.
Maintainer: Bill Wendling
Maintainer-email: morbo@google.com
License: Apache License, Version 2.0
Project-URL: Source, https://github.com/google/yapf
Classifier: Development Status :: 4 - Beta
Classifier: Environment :: Console
Classifier: Intended Audience :: Developers
Classifier: License :: OSI Approved :: Apache Software License
Classifier: Operating System :: OS Independent
Classifier: Programming Language :: Python
Classifier: Programming Language :: Python :: 3 :: Only
Classifier: Programming Language :: Python :: 3.7
Classifier: Programming Language :: Python :: 3.8
Classifier: Programming Language :: Python :: 3.9
Classifier: Programming Language :: Python :: 3.10
Classifier: Programming Language :: Python :: 3.11
Classifier: Topic :: Software Development :: Libraries :: Python Modules
Classifier: Topic :: Software Development :: Quality Assurance
Requires-Python: >=3.7
License-File: LICENSE
License-File: AUTHORS
